{
	"configurations" : 
	[
		{
			"directories" : 
			[
				{
					"build" : ".",
					"jsonFile" : "directory-.-Debug-d0094a50bb2071803777.json",
					"minimumCMakeVersion" : 
					{
						"string" : "3.10"
					},
					"projectIndex" : 0,
					"source" : ".",
					"targetIndexes" : 
					[
						0
					]
				}
			],
			"name" : "Debug",
			"projects" : 
			[
				{
					"directoryIndexes" : 
					[
						0
					],
					"name" : "MultiCoreCacheCoherence",
					"targetIndexes" : 
					[
						0
					]
				}
			],
			"targets" : 
			[
				{
					"directoryIndex" : 0,
					"id" : "MultiCoreCacheCoherence::@6890427a1f51a3e7e1df",
					"jsonFile" : "target-MultiCoreCacheCoherence-Debug-831ce65125874def3337.json",
					"name" : "MultiCoreCacheCoherence",
					"projectIndex" : 0
				}
			]
		}
	],
	"kind" : "codemodel",
	"paths" : 
	{
		"build" : "F:/Progras/Arqui II - Proyecto II/Multi-Core-Cache-Coherence/cmake-build-debug",
		"source" : "F:/Progras/Arqui II - Proyecto II/Multi-Core-Cache-Coherence"
	},
	"version" : 
	{
		"major" : 2,
		"minor" : 7
	}
}
